drip_feed.py
drip/__init__.py
drip/dropper.py
drip/feeder.py
drip/file_dropper.py
drip/utils.py
drip_drip-1.0.0.dist-info/LICENSE.txt
drip_drip-1.0.0.dist-info/METADATA
drip_drip-1.0.0.dist-info/WHEEL
drip_drip-1.0.0.dist-info/entry_points.txt
drip_drip-1.0.0.dist-info/top_level.txt
drip_drip-1.0.0.dist-info/RECORD
