Metadata-Version: 2.1
Name: drip-drip
Version: 1.0.0
Summary: Provides a utility to control automatic execution when conditions are met.
Author-email: Simon Patton <sjpatton@lbl.gov>
License: BSD-3-Clause-LBNL
Keywords: drip,drip feed,drip-drip
Classifier: Development Status :: 5 - Production/Stable
Classifier: Intended Audience :: Developers
Classifier: Topic :: Scientific/Engineering
Classifier: Programming Language :: Python :: 3.10
Requires-Python: <4,>=3.10.6
License-File: LICENSE.txt
